heliport-0.11.0.data/platlib/heliport/.gitignore
heliport-0.11.0.data/platlib/heliport/bigram.bin
heliport-0.11.0.data/platlib/heliport/confidenceThresholds
heliport-0.11.0.data/platlib/heliport/hexagram.bin
heliport-0.11.0.data/platlib/heliport/quadgram.bin
heliport-0.11.0.data/platlib/heliport/quingram.bin
heliport-0.11.0.data/platlib/heliport/trigram.bin
heliport-0.11.0.data/platlib/heliport/unigram.bin
heliport-0.11.0.data/platlib/heliport/word.bin
heliport-0.11.0.dist-info/METADATA
heliport-0.11.0.dist-info/WHEEL
heliport-0.11.0.dist-info/entry_points.txt
heliport-0.11.0.dist-info/licenses/LICENSE
heliport/__init__.py
heliport/heliport.pypy311-pp73-x86_64-linux-gnu.so
heliport-0.11.0.dist-info/RECORD
